django_rest_kakao_auto_reply-0.1.6.dist-info/METADATA
django_rest_kakao_auto_reply-0.1.6.dist-info/RECORD
django_rest_kakao_auto_reply-0.1.6.dist-info/WHEEL
django_rest_kakao_auto_reply-0.1.6.dist-info/top_level.txt
kakao_auto_reply/__init__.py
kakao_auto_reply/decorators.py
kakao_auto_reply/objects.py
kakao_auto_reply/response.py
kakao_auto_reply/routers.py
kakao_auto_reply/viewsets.py
