Metadata-Version: 2.1
Name: django-rest-kakao-auto-reply
Version: 0.1.6
Summary: Make you easy to create kakaotalk plusfriend bot based on Django + DRF
Home-page: https://github.com/iamchanii/django-rest-kakao-auto-reply
Author: iamchanii
Author-email: iamchanii-@naver.com
License: MIT
Keywords: django-rest-kakao-auto-reply
Platform: UNKNOWN
Classifier: Development Status :: 3 - Alpha
Classifier: Framework :: Django :: 2.0
Classifier: Intended Audience :: Developers
Classifier: License :: OSI Approved :: BSD License
Classifier: Natural Language :: English
Classifier: Programming Language :: Python :: 2
Classifier: Programming Language :: Python :: 2.7
Classifier: Programming Language :: Python :: 3
Classifier: Programming Language :: Python :: 3.4
Classifier: Programming Language :: Python :: 3.5
Classifier: Programming Language :: Python :: 3.6
